VLSI Assignment-3/Question 3/C_Path.v
`timescale 1ns/1ps
module CP (
    input clk,
    // input rst,
    input I0,   //I0 = (XR>0)
    input I1,    //I1 = (XR>=YR)
    output reg D0,
    output reg D1,
    output Subtract,
    output Swap,
    output LoadXR,
    output LoadYR,
    output SelectXY
    );  
    // reg DX;
    // reg DY;

    initial begin
        D0 = 1'h0;
        D1 = 1'h0;
    end

    // always @(*) begin
        assign Subtract = (D0 && ~D1);
        assign Swap     = (~D0 && D1);
        assign LoadYR   = ~D0;
        assign LoadXR   = (~D1 || ~D0);
        assign SelectXY = (~D1 && ~D0);
    // end
    always @(posedge clk) begin
        D0  <= ~I0 || I1 || D1;
        D1  <= (D0 && D1) || (~I0 && ~D1) || (~I1 && ~D1);
    end

endmodule

VLSI Assignment-3/Question 3/DP_run_combo.v
`timescale 1ns/1ps
module DataPath (
        input clk,
        input rst,
        input [15:0] X,
        input [15:0] Y,
        output reg [15:0] Z,
        output ZEQ_Flag,
        output LEQ_Flag,
        output reg [15:0] XR,
        output reg [15:0] YR,
        output SelectXY,
        output subFlag,
        output swapFlag,
        output loadXR,
        output loadYR,
        output D0,
        output D1
        );
        initial begin
                Z <=0;
        end
        always @(X or Y or rst) begin
                if(!rst) begin
                        XR=X;
                        YR=Y;
                end
                else begin
                        XR=0;
                        YR=0;
                        Z=0;
                end
        end
        assign ZEQ_Flag = (XR>0);
        assign LEQ_Flag = (XR>=YR);
        always @(negedge clk or X or Y) begin
                if(swapFlag )
                begin
                        XR <=YR;
                        YR <=XR;
                end
                if(subFlag)
                begin
                        XR <= XR - YR;
                end
                if(SelectXY & loadXR)
                begin
                        XR <=X;
                end
                if(SelectXY & loadYR)
                begin
                        YR <=Y;
                end
        end

        always @(XR) begin
                if(!ZEQ_Flag) 
                begin
                    Z <= YR;
                end
        end
        CP CP(.clk(clk),
                    // .rst(rst),
                    .I0(ZEQ_Flag),
                    .I1(LEQ_Flag),
                    .D0(D0),
                    .D1(D1),
                    .Subtract(subFlag),
                    .Swap(swapFlag),
                    .LoadXR(loadXR),
                    .LoadYR(loadYR),
                    .SelectXY(SelectXY));
    
endmodule

VLSI Assignment-3/Question 3/TB.v
`timescale 1ns/1ps
module tb;
    reg clk;
    reg rst;
    reg [15:0] X;
    reg [15:0] Y;
    wire [15:0] Z;
    wire ZEQ_Flag;
    wire LEQ_Flag;
    wire [15:0] XR;
    wire [15:0] YR;
    wire SelectXY;
    wire subFlag;
    wire swapFlag;
    wire loadXR;
    wire loadYR;

    DataPath CP1(.clk(clk),
                    .rst(rst),
                    .X(X),
                    .Y(Y),
                    .Z(Z),
                    .ZEQ_Flag(ZEQ_Flag),
                    .LEQ_Flag(LEQ_Flag),
                    .XR(XR),
                    .YR(YR),
                    .subFlag(subFlag),
                    .swapFlag(swapFlag),
                    .loadXR(loadXR),
                    .loadYR(loadYR),
                    .SelectXY(SelectXY),
                    .D0(D0),
                    .D1(D1));
    initial clk = 0;
    
    initial begin
        $dumpfile("DUMB_OOOLALA.vcd");
     	$dumpvars(0,tb);
        rst = 1'b1; X = 16'd25; Y = 16'd15; #10; 
        rst = 1'b0;
        #300;
        // rst = 1'b1; X = 16'd24; Y = 16'd3; #10; 
        // rst = 1'b0;
        // #400;
        $finish;
    end
    always #10 clk = ~clk;
endmodule

VLSI Assignment-3/Question 3/DUMB_OOOLALA.vcd
$date
	Sun Apr  4 01:18:38 2021
$end
$version
	Icarus Verilog
$end
$timescale
	1ps
$end
$scope module tb $end
$var wire 1 ! swapFlag $end
$var wire 1 " subFlag $end
$var wire 1 # loadYR $end
$var wire 1 $ loadXR $end
$var wire 1 % ZEQ_Flag $end
$var wire 16 & Z [15:0] $end
$var wire 16 ' YR [15:0] $end
$var wire 16 ( XR [15:0] $end
$var wire 1 ) SelectXY $end
$var wire 1 * LEQ_Flag $end
$var wire 1 + D1 $end
$var wire 1 , D0 $end
$var reg 16 - X [15:0] $end
$var reg 16 . Y [15:0] $end
$var reg 1 / clk $end
$var reg 1 0 rst $end
$scope module CP1 $end
$var wire 16 1 X [15:0] $end
$var wire 16 2 Y [15:0] $end
$var wire 1 / clk $end
$var wire 1 0 rst $end
$var wire 1 ! swapFlag $end
$var wire 1 " subFlag $end
$var wire 1 # loadYR $end
$var wire 1 $ loadXR $end
$var wire 1 % ZEQ_Flag $end
$var wire 1 ) SelectXY $end
$var wire 1 * LEQ_Flag $end
$var wire 1 + D1 $end
$var wire 1 , D0 $end
$var reg 16 3 XR [15:0] $end
$var reg 16 4 YR [15:0] $end
$var reg 16 5 Z [15:0] $end
$scope module CP $end
$var wire 1 % I0 $end
$var wire 1 * I1 $end
$var wire 1 $ LoadXR $end
$var wire 1 # LoadYR $end
$var wire 1 ) SelectXY $end
$var wire 1 " Subtract $end
$var wire 1 ! Swap $end
$var wire 1 / clk $end
$var reg 1 , D0 $end
$var reg 1 + D1 $end
$upscope $end
$upscope $end
$upscope $end
$enddefinitions $end
#0
$dumpvars
b0 5
b0 4
b0 3
b1111 2
b11001 1
10
0/
b1111 .
b11001 -
0,
0+
1*
1)
b0 (
b0 '
b0 &
0%
1$
1#
0"
0!
$end
#10000
0)
0#
1"
1,
b1111 '
b1111 4
1%
b11001 (
b11001 3
1/
00
#20000
0*
b1010 (
b1010 3
0/
#30000
1!
1#
0"
1+
0,
1/
#40000
b1010 '
b1010 4
1*
b1111 (
b1111 3
0/
#50000
1"
0!
0#
0+
1,
1/
#60000
0*
b101 (
b101 3
0/
#70000
1!
1#
0"
1+
0,
1/
#80000
b101 '
b101 4
1*
b1010 (
b1010 3
0/
#90000
1"
0!
0#
0+
1,
1/
#100000
b101 (
b101 3
0/
#110000
1/
#120000
b101 &
b101 5
0%
0*
b0 (
b0 3
0/
#130000
0$
0"
1+
1/
